d8s_archives/__init__.py
d8s_archives/archive.py
d8s_archives/archive_temp_utils.py
tests/__init__.py
tests/test_archive.py
tests/test_archive_utils.py
d8s_archives-0.7.0.dist-info/COPYING
d8s_archives-0.7.0.dist-info/COPYING.LESSER
d8s_archives-0.7.0.dist-info/METADATA
d8s_archives-0.7.0.dist-info/WHEEL
d8s_archives-0.7.0.dist-info/top_level.txt
d8s_archives-0.7.0.dist-info/zip-safe
d8s_archives-0.7.0.dist-info/RECORD
